collective.z3cform.datetimewidget-1.2.9-py2.7-nspkg.pth
collective/z3cform/datetimewidget/TODO.txt
collective/z3cform/datetimewidget/__init__.py
collective/z3cform/datetimewidget/configure.zcml
collective/z3cform/datetimewidget/converter.py
collective/z3cform/datetimewidget/converter.txt
collective/z3cform/datetimewidget/i18n.py
collective/z3cform/datetimewidget/interfaces.py
collective/z3cform/datetimewidget/issues.txt
collective/z3cform/datetimewidget/setuphandlers.py
collective/z3cform/datetimewidget/tests.py
collective/z3cform/datetimewidget/widget.py
collective/z3cform/datetimewidget/widget_date.py
collective/z3cform/datetimewidget/widget_date.txt
collective/z3cform/datetimewidget/widget_datetime.py
collective/z3cform/datetimewidget/widget_datetime.txt
collective/z3cform/datetimewidget/widget_monthyear.py
collective/z3cform/datetimewidget/widget_monthyear.txt
collective/z3cform/datetimewidget/docs/conf.py
collective/z3cform/datetimewidget/docs/converters.txt
collective/z3cform/datetimewidget/docs/index.txt
collective/z3cform/datetimewidget/docs/issues.txt
collective/z3cform/datetimewidget/docs/widgets.txt
collective/z3cform/datetimewidget/locales/collective.z3cform.datetimewidget.pot
collective/z3cform/datetimewidget/locales/de/LC_MESSAGES/collective.z3cform.datetimewidget.mo
collective/z3cform/datetimewidget/locales/de/LC_MESSAGES/collective.z3cform.datetimewidget.po
collective/z3cform/datetimewidget/locales/en/LC_MESSAGES/collective.z3cform.datetimewidget.mo
collective/z3cform/datetimewidget/locales/en/LC_MESSAGES/collective.z3cform.datetimewidget.po
collective/z3cform/datetimewidget/locales/es/LC_MESSAGES/collective.z3cform.datetimewidget.mo
collective/z3cform/datetimewidget/locales/es/LC_MESSAGES/collective.z3cform.datetimewidget.po
collective/z3cform/datetimewidget/locales/fr/LC_MESSAGES/collective.z3cform.datetimewidget.mo
collective/z3cform/datetimewidget/locales/fr/LC_MESSAGES/collective.z3cform.datetimewidget.po
collective.z3cform.datetimewidget-1.2.9.dist-info/METADATA
collective.z3cform.datetimewidget-1.2.9.dist-info/WHEEL
collective.z3cform.datetimewidget-1.2.9.dist-info/namespace_packages.txt
collective.z3cform.datetimewidget-1.2.9.dist-info/top_level.txt
collective.z3cform.datetimewidget-1.2.9.dist-info/RECORD
