Metadata-Version: 2.1
Name: collective.z3cform.datetimewidget
Version: 1.2.9
Summary: z3c.form date and datetime widgets
Home-page: https://github.com/collective/collective.z3cform.datetimewidget
Author: Rok Garbas
Author-email: rok@garbas.si
License: GPL version 2
Keywords: z3cform datetime widget
Platform: UNKNOWN
Classifier: Development Status :: 5 - Production/Stable
Classifier: Programming Language :: Python
Classifier: Programming Language :: Python :: 2.7
Classifier: Topic :: Software Development :: Libraries :: Python Modules
Requires-Dist: setuptools
Requires-Dist: zope.i18n
Requires-Dist: z3c.form
Requires-Dist: zope.deprecation
Provides-Extra: test
Requires-Dist: z3c.form ; extra == 'test'
Requires-Dist: zope.browserpage ; extra == 'test'
Requires-Dist: zope.publisher ; extra == 'test'
Requires-Dist: zope.testing ; extra == 'test'
Requires-Dist: zope.traversing ; extra == 'test'
Requires-Dist: zc.buildout ; extra == 'test'
Requires-Dist: Zope2 ; extra == 'test'
